MANIFEST.in
README.rst
setup.py
cmail/__init__.py
cmail/cmail.py
cmail/contacts.json
cmail.egg-info/PKG-INFO
cmail.egg-info/SOURCES.txt
cmail.egg-info/dependency_links.txt
cmail.egg-info/entry_points.txt
cmail.egg-info/not-zip-safe
cmail.egg-info/requires.txt
cmail.egg-info/top_level.txt